{
  "id": "config/bootstrap",
  "title": "Bootstrap Icons",
  "description": "Free, high quality, open source icon library with over 2,000 icons. Include them anyway you like—SVGs, SVG sprite, or web fonts. Use them with or without Bootstrap in any project.",
  "source": "@site/docs/config/bootstrap.md",
  "sourceDirName": "config",
  "slug": "/config/bootstrap",
  "permalink": "/docs/config/bootstrap",
  "draft": false,
  "unlisted": false,
  "editUrl": "https://github.com/facebook/docusaurus/tree/main/packages/create-docusaurus/templates/shared/docs/config/bootstrap.md",
  "tags": [],
  "version": "current",
  "frontMatter": {},
  "sidebar": "tutorialSidebar",
  "previous": {
    "title": "Bootstrap Color Modes",
    "permalink": "/docs/config/bootstrap-color-mode"
  },
  "next": {
    "title": "dev",
    "permalink": "/docs/config/dev"
  }
}